[
  {
    "inputs": [
      {
        "internalType": "address",
        "name": "_owner",
        "type": "address"
      }
    ],
    "stateMutability": "nonpayable",
    "type": "constructor"
  },
  {
    "anonymous": false,
    "inputs": [
      {
        "indexed": true,
        "internalType": "uint256",
        "name": "poolId",
        "type": "uint256"
      },
      {
        "indexed": true,
        "internalType": "address",
        "name": "user",
        "type": "address"
      },
      {
        "indexed": false,
        "internalType": "uint256",
        "name": "amount",
        "type": "uint256"
      }
    ],
    "name": "Claim",
    "type": "event"
  },
  {
    "anonymous": false,
    "inputs": [
      {
        "indexed": true,
        "internalType": "uint256",
        "name": "poolId",
        "type": "uint256"
      },
      {
        "indexed": true,
        "internalType": "address",
        "name": "user",
        "type": "address"
      },
      {
        "indexed": false,
        "internalType": "uint256",
        "name": "amount",
        "type": "uint256"
      }
    ],
    "name": "Deposit",
    "type": "event"
  },
  {
    "anonymous": false,
    "inputs": [
      {
        "indexed": true,
        "internalType": "uint256",
        "name": "poolId",
        "type": "uint256"
      },
      {
        "indexed": true,
        "internalType": "address",
        "name": "funder",
        "type": "address"
      },
      {
        "indexed": false,
        "internalType": "uint256",
        "name": "amount",
        "type": "uint256"
      }
    ],
    "name": "FundRewards",
    "type": "event"
  },
  {
    "anonymous": false,
    "inputs": [
      {
        "indexed": true,
        "internalType": "uint256",
        "name": "poolId",
        "type": "uint256"
      },
      {
        "indexed": false,
        "internalType": "uint256",
        "name": "poolReward",
        "type": "uint256"
      },
      {
        "indexed": false,
        "internalType": "uint256",
        "name": "rewardDurationSeconds",
        "type": "uint256"
      },
      {
        "indexed": false,
        "internalType": "uint256",
        "name": "maxTvl",
        "type": "uint256"
      }
    ],
    "name": "PoolConfigured",
    "type": "event"
  },
  {
    "anonymous": false,
    "inputs": [
      {
        "indexed": true,
        "internalType": "uint256",
        "name": "poolId",
        "type": "uint256"
      },
      {
        "indexed": true,
        "internalType": "address",
        "name": "stakingToken",
        "type": "address"
      },
      {
        "indexed": true,
        "internalType": "address",
        "name": "rewardToken",
        "type": "address"
      },
      {
        "indexed": false,
        "internalType": "uint256",
        "name": "poolReward",
        "type": "uint256"
      },
      {
        "indexed": false,
        "internalType": "uint256",
        "name": "rewardDurationSeconds",
        "type": "uint256"
      },
      {
        "indexed": false,
        "internalType": "uint256",
        "name": "maxTvl",
        "type": "uint256"
      }
    ],
    "name": "PoolCreated",
    "type": "event"
  },
  {
    "anonymous": false,
    "inputs": [
      {
        "indexed": true,
        "internalType": "uint256",
        "name": "poolId",
        "type": "uint256"
      },
      {
        "indexed": true,
        "internalType": "address",
        "name": "user",
        "type": "address"
      },
      {
        "indexed": false,
        "internalType": "uint256",
        "name": "amount",
        "type": "uint256"
      }
    ],
    "name": "Withdraw",
    "type": "event"
  },
  {
    "inputs": [],
    "name": "ACC_PRECISION",
    "outputs": [
      {
        "internalType": "uint256",
        "name": "",
        "type": "uint256"
      }
    ],
    "stateMutability": "view",
    "type": "function"
  },
  {
    "inputs": [
      {
        "internalType": "uint256",
        "name": "",
        "type": "uint256"
      }
    ],
    "name": "activePoolIds",
    "outputs": [
      {
        "internalType": "uint256",
        "name": "",
        "type": "uint256"
      }
    ],
    "stateMutability": "view",
    "type": "function"
  },
  {
    "inputs": [
      {
        "internalType": "uint256",
        "name": "_poolId",
        "type": "uint256"
      }
    ],
    "name": "claim",
    "outputs": [],
    "stateMutability": "nonpayable",
    "type": "function"
  },
  {
    "inputs": [
      {
        "internalType": "address",
        "name": "_stakingToken",
        "type": "address"
      },
      {
        "internalType": "address",
        "name": "_rewardToken",
        "type": "address"
      },
      {
        "internalType": "uint256",
        "name": "_poolReward",
        "type": "uint256"
      },
      {
        "internalType": "uint256",
        "name": "_rewardDurationSeconds",
        "type": "uint256"
      },
      {
        "internalType": "uint256",
        "name": "_maxTvl",
        "type": "uint256"
      }
    ],
    "name": "createPool",
    "outputs": [
      {
        "internalType": "uint256",
        "name": "poolId",
        "type": "uint256"
      }
    ],
    "stateMutability": "nonpayable",
    "type": "function"
  },
  {
    "inputs": [
      {
        "internalType": "uint256",
        "name": "_poolId",
        "type": "uint256"
      },
      {
        "internalType": "uint256",
        "name": "_amount",
        "type": "uint256"
      }
    ],
    "name": "deposit",
    "outputs": [],
    "stateMutability": "nonpayable",
    "type": "function"
  },
  {
    "inputs": [
      {
        "internalType": "uint256",
        "name": "_poolId",
        "type": "uint256"
      },
      {
        "internalType": "address",
        "name": "_to",
        "type": "address"
      }
    ],
    "name": "emergencyWithdrawRewards",
    "outputs": [],
    "stateMutability": "nonpayable",
    "type": "function"
  },
  {
    "inputs": [
      {
        "internalType": "uint256",
        "name": "_poolId",
        "type": "uint256"
      }
    ],
    "name": "fundPoolRewards",
    "outputs": [],
    "stateMutability": "nonpayable",
    "type": "function"
  },
  {
    "inputs": [],
    "name": "getActivePoolIds",
    "outputs": [
      {
        "internalType": "uint256[]",
        "name": "",
        "type": "uint256[]"
      }
    ],
    "stateMutability": "view",
    "type": "function"
  },
  {
    "inputs": [
      {
        "internalType": "uint256",
        "name": "_poolId",
        "type": "uint256"
      }
    ],
    "name": "getPoolInfo",
    "outputs": [
      {
        "components": [
          {
            "internalType": "uint256",
            "name": "poolId",
            "type": "uint256"
          },
          {
            "internalType": "address",
            "name": "stakingToken",
            "type": "address"
          },
          {
            "internalType": "address",
            "name": "rewardToken",
            "type": "address"
          },
          {
            "internalType": "uint256",
            "name": "poolReward",
            "type": "uint256"
          },
          {
            "internalType": "uint256",
            "name": "rewardDurationSeconds",
            "type": "uint256"
          },
          {
            "internalType": "uint256",
            "name": "maxTvl",
            "type": "uint256"
          },
          {
            "internalType": "uint256",
            "name": "rewardPerSecond",
            "type": "uint256"
          },
          {
            "internalType": "uint256",
            "name": "startTime",
            "type": "uint256"
          },
          {
            "internalType": "uint256",
            "name": "endTime",
            "type": "uint256"
          },
          {
            "internalType": "bool",
            "name": "active",
            "type": "bool"
          },
          {
            "internalType": "uint256",
            "name": "createdAt",
            "type": "uint256"
          }
        ],
        "internalType": "struct TiwiStakingPoolFactory.PoolConfig",
        "name": "config",
        "type": "tuple"
      },
      {
        "components": [
          {
            "internalType": "uint256",
            "name": "totalStaked",
            "type": "uint256"
          },
          {
            "internalType": "uint256",
            "name": "accRewardPerShare",
            "type": "uint256"
          },
          {
            "internalType": "uint256",
            "name": "lastRewardTime",
            "type": "uint256"
          }
        ],
        "internalType": "struct TiwiStakingPoolFactory.PoolState",
        "name": "state",
        "type": "tuple"
      }
    ],
    "stateMutability": "view",
    "type": "function"
  },
  {
    "inputs": [
      {
        "internalType": "address",
        "name": "_stakingToken",
        "type": "address"
      },
      {
        "internalType": "address",
        "name": "_rewardToken",
        "type": "address"
      }
    ],
    "name": "getPoolsByTokenPair",
    "outputs": [
      {
        "internalType": "uint256[]",
        "name": "",
        "type": "uint256[]"
      }
    ],
    "stateMutability": "view",
    "type": "function"
  },
  {
    "inputs": [
      {
        "internalType": "uint256",
        "name": "_poolId",
        "type": "uint256"
      },
      {
        "internalType": "address",
        "name": "_user",
        "type": "address"
      }
    ],
    "name": "getUserInfo",
    "outputs": [
      {
        "internalType": "uint256",
        "name": "amount",
        "type": "uint256"
      },
      {
        "internalType": "uint256",
        "name": "rewardDebt",
        "type": "uint256"
      },
      {
        "internalType": "uint256",
        "name": "stakeTime",
        "type": "uint256"
      },
      {
        "internalType": "uint256",
        "name": "pending",
        "type": "uint256"
      }
    ],
    "stateMutability": "view",
    "type": "function"
  },
  {
    "inputs": [],
    "name": "owner",
    "outputs": [
      {
        "internalType": "address",
        "name": "",
        "type": "address"
      }
    ],
    "stateMutability": "view",
    "type": "function"
  },
  {
    "inputs": [
      {
        "internalType": "uint256",
        "name": "_poolId",
        "type": "uint256"
      },
      {
        "internalType": "address",
        "name": "_user",
        "type": "address"
      }
    ],
    "name": "pendingReward",
    "outputs": [
      {
        "internalType": "uint256",
        "name": "",
        "type": "uint256"
      }
    ],
    "stateMutability": "view",
    "type": "function"
  },
  {
    "inputs": [],
    "name": "poolCount",
    "outputs": [
      {
        "internalType": "uint256",
        "name": "",
        "type": "uint256"
      }
    ],
    "stateMutability": "view",
    "type": "function"
  },
  {
    "inputs": [
      {
        "internalType": "uint256",
        "name": "",
        "type": "uint256"
      }
    ],
    "name": "poolExists",
    "outputs": [
      {
        "internalType": "bool",
        "name": "",
        "type": "bool"
      }
    ],
    "stateMutability": "view",
    "type": "function"
  },
  {
    "inputs": [
      {
        "internalType": "uint256",
        "name": "",
        "type": "uint256"
      }
    ],
    "name": "poolState",
    "outputs": [
      {
        "internalType": "uint256",
        "name": "totalStaked",
        "type": "uint256"
      },
      {
        "internalType": "uint256",
        "name": "accRewardPerShare",
        "type": "uint256"
      },
      {
        "internalType": "uint256",
        "name": "lastRewardTime",
        "type": "uint256"
      }
    ],
    "stateMutability": "view",
    "type": "function"
  },
  {
    "inputs": [
      {
        "internalType": "uint256",
        "name": "",
        "type": "uint256"
      }
    ],
    "name": "pools",
    "outputs": [
      {
        "internalType": "uint256",
        "name": "poolId",
        "type": "uint256"
      },
      {
        "internalType": "address",
        "name": "stakingToken",
        "type": "address"
      },
      {
        "internalType": "address",
        "name": "rewardToken",
        "type": "address"
      },
      {
        "internalType": "uint256",
        "name": "poolReward",
        "type": "uint256"
      },
      {
        "internalType": "uint256",
        "name": "rewardDurationSeconds",
        "type": "uint256"
      },
      {
        "internalType": "uint256",
        "name": "maxTvl",
        "type": "uint256"
      },
      {
        "internalType": "uint256",
        "name": "rewardPerSecond",
        "type": "uint256"
      },
      {
        "internalType": "uint256",
        "name": "startTime",
        "type": "uint256"
      },
      {
        "internalType": "uint256",
        "name": "endTime",
        "type": "uint256"
      },
      {
        "internalType": "bool",
        "name": "active",
        "type": "bool"
      },
      {
        "internalType": "uint256",
        "name": "createdAt",
        "type": "uint256"
      }
    ],
    "stateMutability": "view",
    "type": "function"
  },
  {
    "inputs": [
      {
        "internalType": "address",
        "name": "",
        "type": "address"
      },
      {
        "internalType": "address",
        "name": "",
        "type": "address"
      },
      {
        "internalType": "uint256",
        "name": "",
        "type": "uint256"
      }
    ],
    "name": "poolsByTokenPair",
    "outputs": [
      {
        "internalType": "uint256",
        "name": "",
        "type": "uint256"
      }
    ],
    "stateMutability": "view",
    "type": "function"
  },
  {
    "inputs": [
      {
        "internalType": "uint256",
        "name": "_poolId",
        "type": "uint256"
      },
      {
        "internalType": "bool",
        "name": "_active",
        "type": "bool"
      }
    ],
    "name": "setPoolActive",
    "outputs": [],
    "stateMutability": "nonpayable",
    "type": "function"
  },
  {
    "inputs": [
      {
        "internalType": "uint256",
        "name": "_poolId",
        "type": "uint256"
      },
      {
        "internalType": "uint256",
        "name": "_poolReward",
        "type": "uint256"
      },
      {
        "internalType": "uint256",
        "name": "_rewardDurationSeconds",
        "type": "uint256"
      },
      {
        "internalType": "uint256",
        "name": "_maxTvl",
        "type": "uint256"
      }
    ],
    "name": "updatePoolConfig",
    "outputs": [],
    "stateMutability": "nonpayable",
    "type": "function"
  },
  {
    "inputs": [
      {
        "internalType": "uint256",
        "name": "",
        "type": "uint256"
      },
      {
        "internalType": "address",
        "name": "",
        "type": "address"
      }
    ],
    "name": "userInfo",
    "outputs": [
      {
        "internalType": "uint256",
        "name": "amount",
        "type": "uint256"
      },
      {
        "internalType": "uint256",
        "name": "rewardDebt",
        "type": "uint256"
      },
      {
        "internalType": "uint256",
        "name": "stakeTime",
        "type": "uint256"
      }
    ],
    "stateMutability": "view",
    "type": "function"
  },
  {
    "inputs": [
      {
        "internalType": "uint256",
        "name": "_poolId",
        "type": "uint256"
      },
      {
        "internalType": "uint256",
        "name": "_amount",
        "type": "uint256"
      }
    ],
    "name": "withdraw",
    "outputs": [],
    "stateMutability": "nonpayable",
    "type": "function"
  }
]
